Metadata-Version: 2.1
Name: odoo14-addon-account-move-line-sale-info
Version: 14.0.1.0.4
Summary: Introduces the purchase order line to the journal items
Home-page: https://github.com/OCA/account-financial-tools
Author: ForgeFlow S.L., Odoo Community Association (OCA)
Author-email: support@odoo-community.org
License: AGPL-3
Platform: UNKNOWN
Classifier: Programming Language :: Python
Classifier: Framework :: Odoo
Classifier: Framework :: Odoo :: 14.0
Classifier: License :: OSI Approved :: GNU Affero General Public License v3
Requires-Python: >=3.6
Requires-Dist: odoo14-addon-account-move-line-stock-info
Requires-Dist: odoo14-addon-stock-account-prepare-anglo-saxon-out-lines-hook
Requires-Dist: odoo (<14.1dev,>=14.0a)
